{
  "schemaVersion": "nomad-static-weather-v1",
  "regionId": "cl-punta-arenas",
  "month": 8,
  "summary": {
    "temperatureC": 3.1,
    "temperatureMinC": -1.9,
    "temperatureMaxC": 6.9,
    "rainfallMm": 42.4,
    "humidityPct": 81.5,
    "windKph": 35.2,
    "uvIndex": 0.9,
    "uvIndexMax": 2,
    "pm25": 1.7,
    "aqi": 27,
    "waveHeightMinM": 0,
    "waveHeightM": 0.19,
    "waveHeightMaxM": 0.74,
    "wavePeriodS": 2.3,
    "waveDirectionDeg": null,
    "waterTempC": 5.2,
    "climateLastUpdated": "2026-02-08T16:24:55.000Z",
    "airQualityLastUpdated": "2026-02-09T02:44:10.000Z",
    "marineLastUpdated": "2026-02-09T06:00:09.000Z"
  }
}
