{
  "schemaVersion": "nomad-static-weather-v1",
  "regionId": "es-palma",
  "month": 7,
  "summary": {
    "temperatureC": 27.2,
    "temperatureMinC": 23.8,
    "temperatureMaxC": 30.9,
    "rainfallMm": 5.7,
    "humidityPct": 68.3,
    "windKph": 13.8,
    "uvIndex": 8.3,
    "uvIndexMax": 9.8,
    "pm25": 6.8,
    "aqi": 38.6,
    "waveHeightMinM": 0.02,
    "waveHeightM": 0.38,
    "waveHeightMaxM": 1.34,
    "wavePeriodS": 4,
    "waveDirectionDeg": null,
    "waterTempC": 27.74,
    "climateLastUpdated": "2026-02-08T16:24:55.000Z",
    "airQualityLastUpdated": "2026-02-09T02:44:10.000Z",
    "marineLastUpdated": "2026-02-09T05:46:30.000Z"
  }
}
